api/__init__.py
api/namespace_status.py
api/status_dto.py
model/__init__.py
model/status.py
model/user.py
serializer/__init__.py
serializer/status_schema.py
serializer/user_schema.py
EL_Status-1.0.dist-info/METADATA
EL_Status-1.0.dist-info/WHEEL
EL_Status-1.0.dist-info/top_level.txt
EL_Status-1.0.dist-info/RECORD
