Metadata-Version: 2.1
Name: EL-Status
Version: 1.0
Summary: Hackathon 2020 Winter
Home-page: http://www.elpassion.pl/
Author: Kevin Czupryński
Author-email: kewin.czuprynski@elpassion.pl
License: MIT
Platform: UNKNOWN
